odoo/addons/account_fiscal_year_closing/README.rst
odoo/addons/account_fiscal_year_closing/__init__.py
odoo/addons/account_fiscal_year_closing/__manifest__.py
odoo/addons/account_fiscal_year_closing/i18n/account_fiscal_year_closing.pot
odoo/addons/account_fiscal_year_closing/i18n/de.po
odoo/addons/account_fiscal_year_closing/i18n/es.po
odoo/addons/account_fiscal_year_closing/i18n/fr.po
odoo/addons/account_fiscal_year_closing/i18n/hr.po
odoo/addons/account_fiscal_year_closing/i18n/it.po
odoo/addons/account_fiscal_year_closing/i18n/nl_NL.po
odoo/addons/account_fiscal_year_closing/i18n/pt.po
odoo/addons/account_fiscal_year_closing/i18n/pt_BR.po
odoo/addons/account_fiscal_year_closing/migrations/14.0.1.0.3/noupdate_changes.xml
odoo/addons/account_fiscal_year_closing/migrations/14.0.1.0.3/post-migration.py
odoo/addons/account_fiscal_year_closing/models/__init__.py
odoo/addons/account_fiscal_year_closing/models/account_fiscalyear_closing.py
odoo/addons/account_fiscal_year_closing/models/account_fiscalyear_closing_abstract.py
odoo/addons/account_fiscal_year_closing/models/account_fiscalyear_closing_template.py
odoo/addons/account_fiscal_year_closing/models/account_move.py
odoo/addons/account_fiscal_year_closing/readme/CONFIGURE.rst
odoo/addons/account_fiscal_year_closing/readme/CONTRIBUTORS.rst
odoo/addons/account_fiscal_year_closing/readme/DESCRIPTION.rst
odoo/addons/account_fiscal_year_closing/readme/USAGE.rst
odoo/addons/account_fiscal_year_closing/security/account_fiscalyear_closing_security.xml
odoo/addons/account_fiscal_year_closing/security/ir.model.access.csv
odoo/addons/account_fiscal_year_closing/static/description/icon.png
odoo/addons/account_fiscal_year_closing/static/description/icon.svg
odoo/addons/account_fiscal_year_closing/static/description/index.html
odoo/addons/account_fiscal_year_closing/tests/__init__.py
odoo/addons/account_fiscal_year_closing/tests/test_account_fiscal_year_closing.py
odoo14_addon_account_fiscal_year_closing-14.0.1.0.4.dist-info/METADATA
odoo14_addon_account_fiscal_year_closing-14.0.1.0.4.dist-info/WHEEL
odoo14_addon_account_fiscal_year_closing-14.0.1.0.4.dist-info/top_level.txt
odoo14_addon_account_fiscal_year_closing-14.0.1.0.4.dist-info/RECORD
